pycounts/__init__.py
pycounts/data/__init__.py
pycounts/data/flatland.txt
pycounts/datasets.py
pycounts/plotting.py
pycounts/pycounts.py
pycounts-0.4.0.dist-info/LICENSE
pycounts-0.4.0.dist-info/WHEEL
pycounts-0.4.0.dist-info/METADATA
pycounts-0.4.0.dist-info/RECORD
