Metadata-Version: 2.1
Name: pycounts
Version: 0.4.0
Summary: Calculate word counts in a text file!
License: MIT
Author: Tomas Beuzen
Requires-Python: >=3.9,<4.0
Classifier: License :: OSI Approved :: MIT License
Classifier: Programming Language :: Python :: 3
Classifier: Programming Language :: Python :: 3.9
Requires-Dist: matplotlib (>=3.4.3,<4.0.0)
Requires-Dist: myst-nb (>=0.12.3,<0.13.0)
